llama_index/graph_stores/nebula/__init__.py
llama_index/graph_stores/nebula/nebula_graph_store.py
llama_index/graph_stores/nebula/nebula_property_graph.py
llama_index/graph_stores/nebula/utils.py
llama_index_graph_stores_nebula-0.5.0.dist-info/METADATA
llama_index_graph_stores_nebula-0.5.0.dist-info/WHEEL
llama_index_graph_stores_nebula-0.5.0.dist-info/licenses/LICENSE
llama_index_graph_stores_nebula-0.5.0.dist-info/RECORD
