Metadata-Version: 2.4
Name: llama-index-graph-stores-nebula
Version: 0.5.0
Summary: llama-index graph stores nebula integration
Author-email: Your Name <you@example.com>
License-Expression: Apache-2.0
License-File: LICENSE
Requires-Python: <4.0,>=3.9
Requires-Dist: llama-index-core<0.14,>=0.13.0
Requires-Dist: nebula3-python<4,>=3.8.0
